_image/__init__.py
_image/list_colors.py
_image/max_rect.py
_image/sprite.py
_image/tests/__init__.py
_image/tests/test_merge_image.py
unrest/__init__.py
unrest/admin.py
unrest/apps.py
unrest/decorators.py
unrest/managers.py
unrest/models.py
unrest/pagination.py
unrest/settings.py
unrest/urls.py
unrest/utils.py
unrest/views.py
unrest/migrations/__init__.py
unrest/nopass/__init__.py
unrest/nopass/apps.py
unrest/nopass/tests.py
unrest/nopass/urls.py
unrest/nopass/views.py
unrest/nopass/migrations/__init__.py
unrest/user/__init__.py
unrest/user/admin.py
unrest/user/apps.py
unrest/user/forms.py
unrest/user/models.py
unrest/user/tests.py
unrest/user/urls.py
unrest/user/views.py
unrest/user/migrations/0001_initial.py
unrest/user/migrations/0002_auto_20201229_1248.py
unrest/user/migrations/0003_alter_user_id.py
unrest/user/migrations/__init__.py
django_unrest-0.1.11.dist-info/LICENSE
django_unrest-0.1.11.dist-info/METADATA
django_unrest-0.1.11.dist-info/WHEEL
django_unrest-0.1.11.dist-info/top_level.txt
django_unrest-0.1.11.dist-info/RECORD
